statute_matcher_regex/__init__.py
statute_matcher_regex/__main__.py
statute_matcher_regex/assigner.py
statute_matcher_regex/formula/__init__.py
statute_matcher_regex/formula/base.py
statute_matcher_regex/formula/named.py
statute_matcher_regex/formula/provisions.py
statute_matcher_regex/formula/serials.py
statute_matcher_regex/matcher.py
statute_matcher_regex/spanner.py
statute_matcher_regex-0.0.4.dist-info/WHEEL
statute_matcher_regex-0.0.4.dist-info/METADATA
statute_matcher_regex-0.0.4.dist-info/RECORD
